<PositionList><Position><GPSID>VIA_3464</GPSID><UTC>2019-08-05T21:29:27.712-04:00</UTC><UTCTIME>1565054967712</UTCTIME><LATITUDE>44.914943</LATITUDE><LONGITUDE>-76.024705</LONGITUDE><DIRECTION>351.6</DIRECTION><SPEED>32.6</SPEED></Position><Position><GPSID>VIA_3460</GPSID><UTC>2019-08-05T21:29:23.841-04:00</UTC><UTCTIME>1565054963841</UTCTIME><LATITUDE>43.610368</LATITUDE><LONGITUDE>-79.507837</LONGITUDE><DIRECTION>-1.0</DIRECTION><SPEED>0.0</SPEED></Position><Position><GPSID>VIA_7314</GPSID><UTC>2019-08-05T21:29:21.336-04:00</UTC><UTCTIME>1565054961336</UTCTIME><LATITUDE>44.636978</LATITUDE><LONGITUDE>-63.568332</LONGITUDE><DIRECTION>-1.0</DIRECTION><SPEED>0.0</SPEED></Position><Position><GPSID>VIA_3465</GPSID><UTC>2019-08-05T21:29:24.005-04:00</UTC><UTCTIME>1565054964005</UTCTIME><LATITUDE>45.479488</LATITUDE><LONGITUDE>-73.5466</LONGITUDE><DIRECTION>-1.0</DIRECTION><SPEED>0.0</SPEED></Position><Position><GPSID>VIA_4007</GPSID><UTC>2019-08-05T21:29:29.058-04:00</UTC><UTCTIME>1565054969058</UTCTIME><LATITUDE>43.367555</LATITUDE><LONGITUDE>-80.756632</LONGITUDE><DIRECTION>66.9</DIRECTION><SPEED>9.8</SPEED></Position><Position><GPSID>VIA_4002</GPSID><UTC>2019-08-05T21:29:27.542-04:00</UTC><UTCTIME>1565054967542</UTCTIME><LATITUDE>44.216388</LATITUDE><LONGITUDE>-77.168247</LONGITUDE><DIRECTION>256.1</DIRECTION><SPEED>78.6</SPEED></Position><Position><GPSID>VIA_3476</GPSID><UTC>2019-08-05T21:29:28.940-04:00</UTC><UTCTIME>1565054968940</UTCTIME><LATITUDE>42.988063</LATITUDE><LONGITUDE>-81.330217</LONGITUDE><DIRECTION>283.8</DIRECTION><SPEED>20.1</SPEED></Position><Position><GPSID>VIA_4019</GPSID><UTC>2019-08-05T21:29:26.817-04:00</UTC><UTCTIME>1565054966817</UTCTIME><LATITUDE>0.0</LATITUDE><LONGITUDE>0.0</LONGITUDE><DIRECTION>-1.0</DIRECTION><SPEED>0.0</SPEED></Position><Position><GPSID>VIA_3472</GPSID><UTC>2019-08-05T21:29:29.671-04:00</UTC><UTCTIME>1565054969671</UTCTIME><LATITUDE>45.415997</LATITUDE><LONGITUDE>-75.650385</LONGITUDE><DIRECTION>-1.0</DIRECTION><SPEED>0.0</SPEED></Position><Position><GPSID>VIA_7309</GPSID><UTC>2019-08-05T21:29:22.051-04:00</UTC><UTCTIME>1565054962051</UTCTIME><LATITUDE>44.637553</LATITUDE><LONGITUDE>-63.568168</LONGITUDE><DIRECTION>-1.0</DIRECTION><SPEED>0.0</SPEED></Position><Position><GPSID>VIA_4026</GPSID><UTC>2019-08-05T21:29:26.924-04:00</UTC><UTCTIME>1565054966924</UTCTIME><LATITUDE>43.939063</LATITUDE><LONGITUDE>-79.434095</LONGITUDE><DIRECTION>-1.0</DIRECTION><SPEED>0.0</SPEED></Position><Position><GPSID>VIA_3452</GPSID><UTC>2019-08-05T21:29:22.444-04:00</UTC><UTCTIME>1565054962444</UTCTIME><LATITUDE>42.981167</LATITUDE><LONGITUDE>-81.245368</LONGITUDE><DIRECTION>-1.0</DIRECTION><SPEED>0.0</SPEED></Position><Position><GPSID>VIA_7313</GPSID><UTC>2019-08-05T21:29:24.836-04:00</UTC><UTCTIME>1565054964836</UTCTIME><LATITUDE>45.47996</LATITUDE><LONGITUDE>-73.547155</LONGITUDE><DIRECTION>-1.0</DIRECTION><SPEED>0.0</SPEED></Position><Position><GPSID>VIA_4003</GPSID><UTC>2019-08-05T21:29:23.242-04:00</UTC><UTCTIME>1565054963242</UTCTIME><LATITUDE>43.608728</LATITUDE><LONGITUDE>-79.50834</LONGITUDE><DIRECTION>-1.0</DIRECTION><SPEED>0.0</SPEED></Position><Position><GPSID>VIA_4009</GPSID><UTC>2019-08-05T21:29:24.047-04:00</UTC><UTCTIME>1565054964047</UTCTIME><LATITUDE>44.311515</LATITUDE><LONGITUDE>-76.3929</LONGITUDE><DIRECTION>56.9</DIRECTION><SPEED>80.4</SPEED></Position><Position><GPSID>VIA_7308</GPSID><UTC>2019-08-05T21:29:27.974-04:00</UTC><UTCTIME>1565054967974</UTCTIME><LATITUDE>45.476012</LATITUDE><LONGITUDE>-73.551115</LONGITUDE><DIRECTION>-1.0</DIRECTION><SPEED>0.0</SPEED></Position><Position><GPSID>VIA_4005</GPSID><UTC>2019-08-05T21:29:28.131-04:00</UTC><UTCTIME>1565054968131</UTCTIME><LATITUDE>45.481073</LATITUDE><LONGITUDE>-73.545457</LONGITUDE><DIRECTION>-1.0</DIRECTION><SPEED>0.0</SPEED></Position><Position><GPSID>VIA_3352</GPSID><UTC>2019-08-05T21:29:22.167-04:00</UTC><UTCTIME>1565054962167</UTCTIME><LATITUDE>44.868595</LATITUDE><LONGITUDE>-75.299512</LONGITUDE><DIRECTION>59.8</DIRECTION><SPEED>82.4</SPEED></Position><Position><GPSID>VIA_4028</GPSID><UTC>2019-08-05T21:29:28.436-04:00</UTC><UTCTIME>1565054968436</UTCTIME><LATITUDE>44.634522</LATITUDE><LONGITUDE>-63.569158</LONGITUDE><DIRECTION>-1.0</DIRECTION><SPEED>0.0</SPEED></Position><Position><GPSID>VIA_7301</GPSID><UTC>2019-08-05T21:29:23.001-04:00</UTC><UTCTIME>1565054963001</UTCTIME><LATITUDE>45.484708</LATITUDE><LONGITUDE>-73.543282</LONGITUDE><DIRECTION>-1.0</DIRECTION><SPEED>0.0</SPEED></Position><Position><GPSID>VIA_7307</GPSID><UTC>2019-08-05T21:29:26.602-04:00</UTC><UTCTIME>1565054966602</UTCTIME><LATITUDE>45.415748</LATITUDE><LONGITUDE>-75.65048</LONGITUDE><DIRECTION>-1.0</DIRECTION><SPEED>0.0</SPEED></Position><Position><GPSID>VIA_3367</GPSID><UTC>2019-08-05T21:29:22.986-04:00</UTC><UTCTIME>1565054962986</UTCTIME><LATITUDE>44.223412</LATITUDE><LONGITUDE>-76.862533</LONGITUDE><DIRECTION>289.6</DIRECTION><SPEED>82.0</SPEED></Position><Position><GPSID>VIA_3463</GPSID><UTC>2019-08-05T21:29:22.524-04:00</UTC><UTCTIME>1565054962524</UTCTIME><LATITUDE>45.478027</LATITUDE><LONGITUDE>-73.548993</LONGITUDE><DIRECTION>-1.0</DIRECTION><SPEED>0.0</SPEED></Position><Position><GPSID>VIA_3467</GPSID><UTC>2019-08-05T21:29:22.022-04:00</UTC><UTCTIME>1565054962022</UTCTIME><LATITUDE>45.415797</LATITUDE><LONGITUDE>-75.653005</LONGITUDE><DIRECTION>-1.0</DIRECTION><SPEED>0.0</SPEED></Position><Position><GPSID>VIA_3451</GPSID><UTC>2019-08-05T21:29:28.013-04:00</UTC><UTCTIME>1565054968013</UTCTIME><LATITUDE>43.244907</LATITUDE><LONGITUDE>-80.056975</LONGITUDE><DIRECTION>84.0</DIRECTION><SPEED>13.5</SPEED></Position><Position><GPSID>VIA_3466</GPSID><UTC>2019-08-05T21:29:24.136-04:00</UTC><UTCTIME>1565054964136</UTCTIME><LATITUDE>45.481773</LATITUDE><LONGITUDE>-73.545025</LONGITUDE><DIRECTION>-1.0</DIRECTION><SPEED>0.0</SPEED></Position><Position><GPSID>VIA_4025</GPSID><UTC>2019-08-05T21:29:22.264-04:00</UTC><UTCTIME>1565054962264</UTCTIME><LATITUDE>44.63825</LATITUDE><LONGITUDE>-63.569313</LONGITUDE><DIRECTION>-1.0</DIRECTION><SPEED>0.0</SPEED></Position><Position><GPSID>VIA_3455</GPSID><UTC>2019-08-05T21:29:25.993-04:00</UTC><UTCTIME>1565054965993</UTCTIME><LATITUDE>43.244847</LATITUDE><LONGITUDE>-80.05746</LONGITUDE><DIRECTION>85.1</DIRECTION><SPEED>13.5</SPEED></Position><Position><GPSID>VIA_3468</GPSID><UTC>2019-08-05T21:29:25.584-04:00</UTC><UTCTIME>1565054965584</UTCTIME><LATITUDE>45.344875</LATITUDE><LONGITUDE>-74.0951</LONGITUDE><DIRECTION>55.1</DIRECTION><SPEED>66.2</SPEED></Position><Position><GPSID>VIA_3461</GPSID><UTC>2019-08-05T21:29:21.527-04:00</UTC><UTCTIME>1565054961527</UTCTIME><LATITUDE>44.868727</LATITUDE><LONGITUDE>-75.29925</LONGITUDE><DIRECTION>59.4</DIRECTION><SPEED>82.2</SPEED></Position><Position><GPSID>VIA_3471</GPSID><UTC>2019-08-05T21:29:25.311-04:00</UTC><UTCTIME>1565054965311</UTCTIME><LATITUDE>46.748542</LATITUDE><LONGITUDE>-71.332283</LONGITUDE><DIRECTION>248.8</DIRECTION><SPEED>19.4</SPEED></Position><Position><GPSID>VIA_4008</GPSID><UTC>2019-08-05T21:29:29.493-04:00</UTC><UTCTIME>1565054969493</UTCTIME><LATITUDE>43.765368</LATITUDE><LONGITUDE>-79.148995</LONGITUDE><DIRECTION>243.1</DIRECTION><SPEED>63.7</SPEED></Position><Position><GPSID>VIA_3469</GPSID><UTC>2019-08-05T21:29:26.954-04:00</UTC><UTCTIME>1565054966954</UTCTIME><LATITUDE>44.252162</LATITUDE><LONGITUDE>-76.962775</LONGITUDE><DIRECTION>75.2</DIRECTION><SPEED>62.8</SPEED></Position><Position><GPSID>VIA_3462</GPSID><UTC>2019-08-05T21:29:24.097-04:00</UTC><UTCTIME>1565054964097</UTCTIME><LATITUDE>43.644218</LATITUDE><LONGITUDE>-79.380115</LONGITUDE><DIRECTION>-1.0</DIRECTION><SPEED>0.0</SPEED></Position><Position><GPSID>VIA_3459</GPSID><UTC>2019-08-05T21:29:23.934-04:00</UTC><UTCTIME>1565054963934</UTCTIME><LATITUDE>44.223463</LATITUDE><LONGITUDE>-76.862713</LONGITUDE><DIRECTION>289.5</DIRECTION><SPEED>82.0</SPEED></Position><Position><GPSID>VIA_3470</GPSID><UTC>2019-08-05T21:29:30.170-04:00</UTC><UTCTIME>1565054970170</UTCTIME><LATITUDE>45.416122</LATITUDE><LONGITUDE>-75.649948</LONGITUDE><DIRECTION>-1.0</DIRECTION><SPEED>0.0</SPEED></Position><Position><GPSID>VIA_3456</GPSID><UTC>2019-08-05T21:29:28.625-04:00</UTC><UTCTIME>1565054968625</UTCTIME><LATITUDE>42.323323</LATITUDE><LONGITUDE>-82.401633</LONGITUDE><DIRECTION>248.8</DIRECTION><SPEED>28.9</SPEED></Position><Position><GPSID>VIA_3475</GPSID><UTC>2019-08-05T21:29:27.461-04:00</UTC><UTCTIME>1565054967461</UTCTIME><LATITUDE>46.819877</LATITUDE><LONGITUDE>-71.214772</LONGITUDE><DIRECTION>-1.0</DIRECTION><SPEED>0.0</SPEED></Position><Position><GPSID>VIA_3477</GPSID><UTC>2019-08-05T21:29:23.620-04:00</UTC><UTCTIME>1565054963620</UTCTIME><LATITUDE>43.146902</LATITUDE><LONGITUDE>-80.260005</LONGITUDE><DIRECTION>263.4</DIRECTION><SPEED>16.7</SPEED></Position><Position><GPSID>VIA_3458</GPSID><UTC>2019-08-05T21:29:29.006-04:00</UTC><UTCTIME>1565054969006</UTCTIME><LATITUDE>42.981075</LATITUDE><LONGITUDE>-81.245642</LONGITUDE><DIRECTION>-1.0</DIRECTION><SPEED>0.0</SPEED></Position><Position><GPSID>VIA_4004</GPSID><UTC>2019-08-05T21:29:21.167-04:00</UTC><UTCTIME>1565054961167</UTCTIME><LATITUDE>45.343097</LATITUDE><LONGITUDE>-75.702922</LONGITUDE><DIRECTION>43.6</DIRECTION><SPEED>20.8</SPEED></Position><Position><GPSID>VIA_4004</GPSID><UTC>2019-08-05T21:29:01.168-04:00</UTC><UTCTIME>1565054941168</UTCTIME><LATITUDE>45.341467</LATITUDE><LONGITUDE>-75.704417</LONGITUDE><DIRECTION>28.5</DIRECTION><SPEED>21.4</SPEED></Position><Position><GPSID>VIA_3461</GPSID><UTC>2019-08-05T21:29:01.527-04:00</UTC><UTCTIME>1565054941527</UTCTIME><LATITUDE>44.864427</LATITUDE><LONGITUDE>-75.308113</LONGITUDE><DIRECTION>54.4</DIRECTION><SPEED>82.3</SPEED></Position><Position><GPSID>VIA_3467</GPSID><UTC>2019-08-05T21:29:02.024-04:00</UTC><UTCTIME>1565054942024</UTCTIME><LATITUDE>45.415777</LATITUDE><LONGITUDE>-75.653023</LONGITUDE><DIRECTION>-1.0</DIRECTION><SPEED>0.0</SPEED></Position><Position><GPSID>VIA_3352</GPSID><UTC>2019-08-05T21:29:02.167-04:00</UTC><UTCTIME>1565054942167</UTCTIME><LATITUDE>44.864287</LATITUDE><LONGITUDE>-75.308368</LONGITUDE><DIRECTION>54.7</DIRECTION><SPEED>82.4</SPEED></Position><Position><GPSID>VIA_4003</GPSID><UTC>2019-08-05T21:29:02.242-04:00</UTC><UTCTIME>1565054942242</UTCTIME><LATITUDE>43.608797</LATITUDE><LONGITUDE>-79.508243</LONGITUDE><DIRECTION>-1.0</DIRECTION><SPEED>0.0</SPEED></Position><Position><GPSID>VIA_7314</GPSID><UTC>2019-08-05T21:29:02.335-04:00</UTC><UTCTIME>1565054942335</UTCTIME><LATITUDE>44.636977</LATITUDE><LONGITUDE>-63.568332</LONGITUDE><DIRECTION>-1.0</DIRECTION><SPEED>0.0</SPEED></Position><Position><GPSID>VIA_3452</GPSID><UTC>2019-08-05T21:29:02.444-04:00</UTC><UTCTIME>1565054942444</UTCTIME><LATITUDE>42.98119</LATITUDE><LONGITUDE>-81.24538</LONGITUDE><DIRECTION>-1.0</DIRECTION><SPEED>0.0</SPEED></Position><Position><GPSID>VIA_3477</GPSID><UTC>2019-08-05T21:29:02.621-04:00</UTC><UTCTIME>1565054942621</UTCTIME><LATITUDE>43.147252</LATITUDE><LONGITUDE>-80.25813</LONGITUDE><DIRECTION>242.0</DIRECTION><SPEED>11.8</SPEED></Position><Position><GPSID>VIA_3367</GPSID><UTC>2019-08-05T21:29:02.985-04:00</UTC><UTCTIME>1565054942985</UTCTIME><LATITUDE>44.22087</LATITUDE><LONGITUDE>-76.852622</LONGITUDE><DIRECTION>289.6</DIRECTION><SPEED>79.5</SPEED></Position><Position><GPSID>VIA_7301</GPSID><UTC>2019-08-05T21:29:03.001-04:00</UTC><UTCTIME>1565054943001</UTCTIME><LATITUDE>45.484708</LATITUDE><LONGITUDE>-73.543282</LONGITUDE><DIRECTION>-1.0</DIRECTION><SPEED>0.0</SPEED></Position><Position><GPSID>VIA_3465</GPSID><UTC>2019-08-05T21:29:03.005-04:00</UTC><UTCTIME>1565054943005</UTCTIME><LATITUDE>45.47949</LATITUDE><LONGITUDE>-73.546598</LONGITUDE><DIRECTION>-1.0</DIRECTION><SPEED>0.0</SPEED></Position><Position><GPSID>VIA_7309</GPSID><UTC>2019-08-05T21:29:03.050-04:00</UTC><UTCTIME>1565054943050</UTCTIME><LATITUDE>44.63755</LATITUDE><LONGITUDE>-63.56817</LONGITUDE><DIRECTION>-1.0</DIRECTION><SPEED>0.0</SPEED></Position><Position><GPSID>VIA_3466</GPSID><UTC>2019-08-05T21:29:03.140-04:00</UTC><UTCTIME>1565054943140</UTCTIME><LATITUDE>45.481775</LATITUDE><LONGITUDE>-73.545027</LONGITUDE><DIRECTION>-1.0</DIRECTION><SPEED>0.0</SPEED></Position><Position><GPSID>VIA_4025</GPSID><UTC>2019-08-05T21:29:03.261-04:00</UTC><UTCTIME>1565054943261</UTCTIME><LATITUDE>44.63825</LATITUDE><LONGITUDE>-63.569313</LONGITUDE><DIRECTION>-1.0</DIRECTION><SPEED>0.0</SPEED></Position><Position><GPSID>VIA_3463</GPSID><UTC>2019-08-05T21:29:03.529-04:00</UTC><UTCTIME>1565054943529</UTCTIME><LATITUDE>45.478027</LATITUDE><LONGITUDE>-73.548985</LONGITUDE><DIRECTION>232.3</DIRECTION><SPEED>2.0</SPEED></Position><Position><GPSID>VIA_7313</GPSID><UTC>2019-08-05T21:29:03.835-04:00</UTC><UTCTIME>1565054943835</UTCTIME><LATITUDE>45.479958</LATITUDE><LONGITUDE>-73.54715</LONGITUDE><DIRECTION>-1.0</DIRECTION><SPEED>0.0</SPEED></Position><Position><GPSID>VIA_3460</GPSID><UTC>2019-08-05T21:29:03.841-04:00</UTC><UTCTIME>1565054943841</UTCTIME><LATITUDE>43.610368</LATITUDE><LONGITUDE>-79.507863</LONGITUDE><DIRECTION>-1.0</DIRECTION><SPEED>0.0</SPEED></Position><Position><GPSID>VIA_3459</GPSID><UTC>2019-08-05T21:29:03.934-04:00</UTC><UTCTIME>1565054943934</UTCTIME><LATITUDE>44.220918</LATITUDE><LONGITUDE>-76.85279</LONGITUDE><DIRECTION>289.6</DIRECTION><SPEED>79.5</SPEED></Position><Position><GPSID>VIA_4009</GPSID><UTC>2019-08-05T21:29:04.047-04:00</UTC><UTCTIME>1565054944047</UTCTIME><LATITUDE>44.307407</LATITUDE><LONGITUDE>-76.401652</LONGITUDE><DIRECTION>56.9</DIRECTION><SPEED>81.7</SPEED></Position><Position><GPSID>VIA_3462</GPSID><UTC>2019-08-05T21:29:04.097-04:00</UTC><UTCTIME>1565054944097</UTCTIME><LATITUDE>43.64419</LATITUDE><LONGITUDE>-79.380075</LONGITUDE><DIRECTION>-1.0</DIRECTION><SPEED>0.0</SPEED></Position><Position><GPSID>VIA_3471</GPSID><UTC>2019-08-05T21:29:05.309-04:00</UTC><UTCTIME>1565054945309</UTCTIME><LATITUDE>46.749467</LATITUDE><LONGITUDE>-71.328765</LONGITUDE><DIRECTION>249.3</DIRECTION><SPEED>35.7</SPEED></Position><Position><GPSID>VIA_4026</GPSID><UTC>2019-08-05T21:29:05.924-04:00</UTC><UTCTIME>1565054945924</UTCTIME><LATITUDE>43.939063</LATITUDE><LONGITUDE>-79.434095</LONGITUDE><DIRECTION>-1.0</DIRECTION><SPEED>0.0</SPEED></Position><Position><GPSID>VIA_3455</GPSID><UTC>2019-08-05T21:29:05.993-04:00</UTC><UTCTIME>1565054945993</UTCTIME><LATITUDE>43.244705</LATITUDE><LONGITUDE>-80.059317</LONGITUDE><DIRECTION>83.0</DIRECTION><SPEED>18.0</SPEED></Position><Position><GPSID>VIA_3468</GPSID><UTC>2019-08-05T21:29:06.583-04:00</UTC><UTCTIME>1565054946583</UTCTIME><LATITUDE>45.341315</LATITUDE><LONGITUDE>-74.10233</LONGITUDE><DIRECTION>55.1</DIRECTION><SPEED>75.8</SPEED></Position><Position><GPSID>VIA_4019</GPSID><UTC>2019-08-05T21:29:06.817-04:00</UTC><UTCTIME>1565054946817</UTCTIME><LATITUDE>0.0</LATITUDE><LONGITUDE>0.0</LONGITUDE><DIRECTION>-1.0</DIRECTION><SPEED>0.0</SPEED></Position><Position><GPSID>VIA_3469</GPSID><UTC>2019-08-05T21:29:06.953-04:00</UTC><UTCTIME>1565054946953</UTCTIME><LATITUDE>44.25055</LATITUDE><LONGITUDE>-76.971265</LONGITUDE><DIRECTION>75.1</DIRECTION><SPEED>74.0</SPEED></Position><Position><GPSID>VIA_7307</GPSID><UTC>2019-08-05T21:29:07.598-04:00</UTC><UTCTIME>1565054947598</UTCTIME><LATITUDE>45.415755</LATITUDE><LONGITUDE>-75.650467</LONGITUDE><DIRECTION>-1.0</DIRECTION><SPEED>0.0</SPEED></Position><Position><GPSID>VIA_3464</GPSID><UTC>2019-08-05T21:29:07.711-04:00</UTC><UTCTIME>1565054947711</UTCTIME><LATITUDE>44.91246</LATITUDE><LONGITUDE>-76.02401</LONGITUDE><DIRECTION>338.9</DIRECTION><SPEED>21.2</SPEED></Position><Position><GPSID>VIA_3451</GPSID><UTC>2019-08-05T21:29:08.012-04:00</UTC><UTCTIME>1565054948012</UTCTIME><LATITUDE>43.244748</LATITUDE><LONGITUDE>-80.05878</LONGITUDE><DIRECTION>83.2</DIRECTION><SPEED>17.1</SPEED></Position><Position><GPSID>VIA_4007</GPSID><UTC>2019-08-05T21:29:08.058-04:00</UTC><UTCTIME>1565054948058</UTCTIME><LATITUDE>43.367208</LATITUDE><LONGITUDE>-80.757798</LONGITUDE><DIRECTION>68.5</DIRECTION><SPEED>9.3</SPEED></Position><Position><GPSID>VIA_4005</GPSID><UTC>2019-08-05T21:29:08.131-04:00</UTC><UTCTIME>1565054948131</UTCTIME><LATITUDE>45.481075</LATITUDE><LONGITUDE>-73.545457</LONGITUDE><DIRECTION>-1.0</DIRECTION><SPEED>0.0</SPEED></Position><Position><GPSID>VIA_4028</GPSID><UTC>2019-08-05T21:29:08.437-04:00</UTC><UTCTIME>1565054948437</UTCTIME><LATITUDE>44.634545</LATITUDE><LONGITUDE>-63.569193</LONGITUDE><DIRECTION>-1.0</DIRECTION><SPEED>0.0</SPEED></Position><Position><GPSID>VIA_3475</GPSID><UTC>2019-08-05T21:29:08.460-04:00</UTC><UTCTIME>1565054948460</UTCTIME><LATITUDE>46.819877</LATITUDE><LONGITUDE>-71.214772</LONGITUDE><DIRECTION>-1.0</DIRECTION><SPEED>0.0</SPEED></Position><Position><GPSID>VIA_4002</GPSID><UTC>2019-08-05T21:29:08.538-04:00</UTC><UTCTIME>1565054948538</UTCTIME><LATITUDE>44.21807</LATITUDE><LONGITUDE>-77.158897</LONGITUDE><DIRECTION>256.0</DIRECTION><SPEED>79.6</SPEED></Position><Position><GPSID>VIA_3456</GPSID><UTC>2019-08-05T21:29:08.624-04:00</UTC><UTCTIME>1565054948624</UTCTIME><LATITUDE>42.324232</LATITUDE><LONGITUDE>-82.398463</LONGITUDE><DIRECTION>249.0</DIRECTION><SPEED>25.6</SPEED></Position><Position><GPSID>VIA_3476</GPSID><UTC>2019-08-05T21:29:08.940-04:00</UTC><UTCTIME>1565054948940</UTCTIME><LATITUDE>42.987612</LATITUDE><LONGITUDE>-81.327647</LONGITUDE><DIRECTION>283.6</DIRECTION><SPEED>23.5</SPEED></Position><Position><GPSID>VIA_7308</GPSID><UTC>2019-08-05T21:29:08.974-04:00</UTC><UTCTIME>1565054948974</UTCTIME><LATITUDE>45.47601</LATITUDE><LONGITUDE>-73.551117</LONGITUDE><DIRECTION>-1.0</DIRECTION><SPEED>0.0</SPEED></Position><Position><GPSID>VIA_3458</GPSID><UTC>2019-08-05T21:29:09.006-04:00</UTC><UTCTIME>1565054949006</UTCTIME><LATITUDE>42.981052</LATITUDE><LONGITUDE>-81.245638</LONGITUDE><DIRECTION>-1.0</DIRECTION><SPEED>0.0</SPEED></Position><Position><GPSID>VIA_4008</GPSID><UTC>2019-08-05T21:29:09.495-04:00</UTC><UTCTIME>1565054949495</UTCTIME><LATITUDE>43.769027</LATITUDE><LONGITUDE>-79.142368</LONGITUDE><DIRECTION>229.2</DIRECTION><SPEED>67.8</SPEED></Position><Position><GPSID>VIA_3472</GPSID><UTC>2019-08-05T21:29:09.670-04:00</UTC><UTCTIME>1565054949670</UTCTIME><LATITUDE>45.415998</LATITUDE><LONGITUDE>-75.650385</LONGITUDE><DIRECTION>-1.0</DIRECTION><SPEED>0.0</SPEED></Position><Position><GPSID>VIA_3470</GPSID><UTC>2019-08-05T21:29:10.170-04:00</UTC><UTCTIME>1565054950170</UTCTIME><LATITUDE>45.416118</LATITUDE><LONGITUDE>-75.64995</LONGITUDE><DIRECTION>-1.0</DIRECTION><SPEED>0.0</SPEED></Position><Position><GPSID>VIA_4004</GPSID><UTC>2019-08-05T21:29:11.168-04:00</UTC><UTCTIME>1565054951168</UTCTIME><LATITUDE>45.342327</LATITUDE><LONGITUDE>-75.703748</LONGITUDE><DIRECTION>30.9</DIRECTION><SPEED>21.1</SPEED></Position><Position><GPSID>VIA_3461</GPSID><UTC>2019-08-05T21:29:11.527-04:00</UTC><UTCTIME>1565054951527</UTCTIME><LATITUDE>44.866643</LATITUDE><LONGITUDE>-75.303748</LONGITUDE><DIRECTION>54.8</DIRECTION><SPEED>82.3</SPEED></Position><Position><GPSID>VIA_3467</GPSID><UTC>2019-08-05T21:29:12.023-04:00</UTC><UTCTIME>1565054952023</UTCTIME><LATITUDE>45.415783</LATITUDE><LONGITUDE>-75.65302</LONGITUDE><DIRECTION>-1.0</DIRECTION><SPEED>0.0</SPEED></Position><Position><GPSID>VIA_3352</GPSID><UTC>2019-08-05T21:29:12.167-04:00</UTC><UTCTIME>1565054952167</UTCTIME><LATITUDE>44.866498</LATITUDE><LONGITUDE>-75.303992</LONGITUDE><DIRECTION>54.7</DIRECTION><SPEED>82.5</SPEED></Position><Position><GPSID>VIA_4003</GPSID><UTC>2019-08-05T21:29:12.242-04:00</UTC><UTCTIME>1565054952242</UTCTIME><LATITUDE>43.608827</LATITUDE><LONGITUDE>-79.508252</LONGITUDE><DIRECTION>-1.0</DIRECTION><SPEED>0.0</SPEED></Position><Position><GPSID>VIA_4025</GPSID><UTC>2019-08-05T21:29:12.262-04:00</UTC><UTCTIME>1565054952262</UTCTIME><LATITUDE>44.63825</LATITUDE><LONGITUDE>-63.569313</LONGITUDE><DIRECTION>-1.0</DIRECTION><SPEED>0.0</SPEED></Position><Position><GPSID>VIA_7314</GPSID><UTC>2019-08-05T21:29:12.338-04:00</UTC><UTCTIME>1565054952338</UTCTIME><LATITUDE>44.636978</LATITUDE><LONGITUDE>-63.568332</LONGITUDE><DIRECTION>-1.0</DIRECTION><SPEED>0.0</SPEED></Position><Position><GPSID>VIA_3459</GPSID><UTC>2019-08-05T21:29:12.934-04:00</UTC><UTCTIME>1565054952934</UTCTIME><LATITUDE>44.222053</LATITUDE><LONGITUDE>-76.857217</LONGITUDE><DIRECTION>289.6</DIRECTION><SPEED>81.8</SPEED></Position><Position><GPSID>VIA_3367</GPSID><UTC>2019-08-05T21:29:12.985-04:00</UTC><UTCTIME>1565054952985</UTCTIME><LATITUDE>44.22213</LATITUDE><LONGITUDE>-76.857533</LONGITUDE><DIRECTION>289.6</DIRECTION><SPEED>81.9</SPEED></Position><Position><GPSID>VIA_7301</GPSID><UTC>2019-08-05T21:29:13.002-04:00</UTC><UTCTIME>1565054953002</UTCTIME><LATITUDE>45.484708</LATITUDE><LONGITUDE>-73.543282</LONGITUDE><DIRECTION>-1.0</DIRECTION><SPEED>0.0</SPEED></Position><Position><GPSID>VIA_3465</GPSID><UTC>2019-08-05T21:29:13.005-04:00</UTC><UTCTIME>1565054953005</UTCTIME><LATITUDE>45.47949</LATITUDE><LONGITUDE>-73.5466</LONGITUDE><DIRECTION>-1.0</DIRECTION><SPEED>0.0</SPEED></Position><Position><GPSID>VIA_7309</GPSID><UTC>2019-08-05T21:29:13.050-04:00</UTC><UTCTIME>1565054953050</UTCTIME><LATITUDE>44.637552</LATITUDE><LONGITUDE>-63.56817</LONGITUDE><DIRECTION>-1.0</DIRECTION><SPEED>0.0</SPEED></Position><Position><GPSID>VIA_3452</GPSID><UTC>2019-08-05T21:29:13.444-04:00</UTC><UTCTIME>1565054953444</UTCTIME><LATITUDE>42.981177</LATITUDE><LONGITUDE>-81.245378</LONGITUDE><DIRECTION>-1.0</DIRECTION><SPEED>0.0</SPEED></Position><Position><GPSID>VIA_3463</GPSID><UTC>2019-08-05T21:29:13.529-04:00</UTC><UTCTIME>1565054953529</UTCTIME><LATITUDE>45.478023</LATITUDE><LONGITUDE>-73.548995</LONGITUDE><DIRECTION>-1.0</DIRECTION><SPEED>0.0</SPEED></Position><Position><GPSID>VIA_3477</GPSID><UTC>2019-08-05T21:29:13.621-04:00</UTC><UTCTIME>1565054953621</UTCTIME><LATITUDE>43.147017</LATITUDE><LONGITUDE>-80.25901</LONGITUDE><DIRECTION>254.4</DIRECTION><SPEED>14.4</SPEED></Position><Position><GPSID>VIA_3460</GPSID><UTC>2019-08-05T21:29:13.841-04:00</UTC><UTCTIME>1565054953841</UTCTIME><LATITUDE>43.610362</LATITUDE><LONGITUDE>-79.50785</LONGITUDE><DIRECTION>-1.0</DIRECTION><SPEED>0.0</SPEED></Position><Position><GPSID>VIA_4009</GPSID><UTC>2019-08-05T21:29:14.047-04:00</UTC><UTCTIME>1565054954047</UTCTIME><LATITUDE>44.30947</LATITUDE><LONGITUDE>-76.397258</LONGITUDE><DIRECTION>56.9</DIRECTION><SPEED>81.1</SPEED></Position><Position><GPSID>VIA_3462</GPSID><UTC>2019-08-05T21:29:14.097-04:00</UTC><UTCTIME>1565054954097</UTCTIME><LATITUDE>43.644078</LATITUDE><LONGITUDE>-79.380078</LONGITUDE><DIRECTION>-1.0</DIRECTION><SPEED>0.0</SPEED></Position><Position><GPSID>VIA_3466</GPSID><UTC>2019-08-05T21:29:14.140-04:00</UTC><UTCTIME>1565054954140</UTCTIME><LATITUDE>45.481773</LATITUDE><LONGITUDE>-73.545025</LONGITUDE><DIRECTION>-1.0</DIRECTION><SPEED>0.0</SPEED></Position><Position><GPSID>VIA_7313</GPSID><UTC>2019-08-05T21:29:14.835-04:00</UTC><UTCTIME>1565054954835</UTCTIME><LATITUDE>45.479958</LATITUDE><LONGITUDE>-73.547153</LONGITUDE><DIRECTION>-1.0</DIRECTION><SPEED>0.0</SPEED></Position><Position><GPSID>VIA_3455</GPSID><UTC>2019-08-05T21:29:14.994-04:00</UTC><UTCTIME>1565054954994</UTCTIME><LATITUDE>43.244773</LATITUDE><LONGITUDE>-80.058403</LONGITUDE><DIRECTION>84.5</DIRECTION><SPEED>15.0</SPEED></Position><Position><GPSID>VIA_3471</GPSID><UTC>2019-08-05T21:29:15.311-04:00</UTC><UTCTIME>1565054955311</UTCTIME><LATITUDE>46.748938</LATITUDE><LONGITUDE>-71.330793</LONGITUDE><DIRECTION>249.5</DIRECTION><SPEED>27.9</SPEED></Position><Position><GPSID>VIA_3468</GPSID><UTC>2019-08-05T21:29:15.584-04:00</UTC><UTCTIME>1565054955584</UTCTIME><LATITUDE>45.343063</LATITUDE><LONGITUDE>-74.09878</LONGITUDE><DIRECTION>55.1</DIRECTION><SPEED>72.0</SPEED></Position><Position><GPSID>VIA_4019</GPSID><UTC>2019-08-05T21:29:15.817-04:00</UTC><UTCTIME>1565054955817</UTCTIME><LATITUDE>0.0</LATITUDE><LONGITUDE>0.0</LONGITUDE><DIRECTION>-1.0</DIRECTION><SPEED>0.0</SPEED></Position><Position><GPSID>VIA_4026</GPSID><UTC>2019-08-05T21:29:16.924-04:00</UTC><UTCTIME>1565054956924</UTCTIME><LATITUDE>43.939063</LATITUDE><LONGITUDE>-79.434095</LONGITUDE><DIRECTION>-1.0</DIRECTION><SPEED>0.0</SPEED></Position><Position><GPSID>VIA_3469</GPSID><UTC>2019-08-05T21:29:16.953-04:00</UTC><UTCTIME>1565054956953</UTCTIME><LATITUDE>44.251388</LATITUDE><LONGITUDE>-76.966842</LONGITUDE><DIRECTION>75.2</DIRECTION><SPEED>69.3</SPEED></Position><Position><GPSID>VIA_4005</GPSID><UTC>2019-08-05T21:29:17.131-04:00</UTC><UTCTIME>1565054957131</UTCTIME><LATITUDE>45.481075</LATITUDE><LONGITUDE>-73.545457</LONGITUDE><DIRECTION>-1.0</DIRECTION><SPEED>0.0</SPEED></Position><Position><GPSID>VIA_4002</GPSID><UTC>2019-08-05T21:29:17.537-04:00</UTC><UTCTIME>1565054957537</UTCTIME><LATITUDE>44.217272</LATITUDE><LONGITUDE>-77.163342</LONGITUDE><DIRECTION>256.0</DIRECTION><SPEED>78.5</SPEED></Position><Position><GPSID>VIA_7307</GPSID><UTC>2019-08-05T21:29:17.598-04:00</UTC><UTCTIME>1565054957598</UTCTIME><LATITUDE>45.41575</LATITUDE><LONGITUDE>-75.650475</LONGITUDE><DIRECTION>-1.0</DIRECTION><SPEED>0.0</SPEED></Position><Position><GPSID>VIA_3464</GPSID><UTC>2019-08-05T21:29:17.713-04:00</UTC><UTCTIME>1565054957713</UTCTIME><LATITUDE>44.913555</LATITUDE><LONGITUDE>-76.024412</LONGITUDE><DIRECTION>350.3</DIRECTION><SPEED>26.5</SPEED></Position><Position><GPSID>VIA_3451</GPSID><UTC>2019-08-05T21:29:18.012-04:00</UTC><UTCTIME>1565054958012</UTCTIME><LATITUDE>43.244838</LATITUDE><LONGITUDE>-80.057817</LONGITUDE><DIRECTION>80.2</DIRECTION><SPEED>14.0</SPEED></Position><Position><GPSID>VIA_4007</GPSID><UTC>2019-08-05T21:29:18.058-04:00</UTC><UTCTIME>1565054958058</UTCTIME><LATITUDE>43.367368</LATITUDE><LONGITUDE>-80.757252</LONGITUDE><DIRECTION>67.7</DIRECTION><SPEED>9.6</SPEED></Position><Position><GPSID>VIA_4028</GPSID><UTC>2019-08-05T21:29:18.435-04:00</UTC><UTCTIME>1565054958435</UTCTIME><LATITUDE>44.634535</LATITUDE><LONGITUDE>-63.569187</LONGITUDE><DIRECTION>-1.0</DIRECTION><SPEED>0.0</SPEED></Position><Position><GPSID>VIA_3475</GPSID><UTC>2019-08-05T21:29:18.456-04:00</UTC><UTCTIME>1565054958456</UTCTIME><LATITUDE>46.819877</LATITUDE><LONGITUDE>-71.214772</LONGITUDE><DIRECTION>-1.0</DIRECTION><SPEED>0.0</SPEED></Position><Position><GPSID>VIA_3456</GPSID><UTC>2019-08-05T21:29:18.624-04:00</UTC><UTCTIME>1565054958624</UTCTIME><LATITUDE>42.323792</LATITUDE><LONGITUDE>-82.4</LONGITUDE><DIRECTION>248.9</DIRECTION><SPEED>26.9</SPEED></Position><Position><GPSID>VIA_3476</GPSID><UTC>2019-08-05T21:29:18.940-04:00</UTC><UTCTIME>1565054958940</UTCTIME><LATITUDE>42.987843</LATITUDE><LONGITUDE>-81.32897</LONGITUDE><DIRECTION>283.5</DIRECTION><SPEED>20.6</SPEED></Position><Position><GPSID>VIA_7308</GPSID><UTC>2019-08-05T21:29:18.974-04:00</UTC><UTCTIME>1565054958974</UTCTIME><LATITUDE>45.476012</LATITUDE><LONGITUDE>-73.551115</LONGITUDE><DIRECTION>-1.0</DIRECTION><SPEED>0.0</SPEED></Position><Position><GPSID>VIA_3458</GPSID><UTC>2019-08-05T21:29:19.006-04:00</UTC><UTCTIME>1565054959006</UTCTIME><LATITUDE>42.981062</LATITUDE><LONGITUDE>-81.24564</LONGITUDE><DIRECTION>-1.0</DIRECTION><SPEED>0.0</SPEED></Position><Position><GPSID>VIA_4008</GPSID><UTC>2019-08-05T21:29:19.493-04:00</UTC><UTCTIME>1565054959493</UTCTIME><LATITUDE>43.767017</LATITUDE><LONGITUDE>-79.145583</LONGITUDE><DIRECTION>228.8</DIRECTION><SPEED>65.5</SPEED></Position><Position><GPSID>VIA_3472</GPSID><UTC>2019-08-05T21:29:19.671-04:00</UTC><UTCTIME>1565054959671</UTCTIME><LATITUDE>45.415997</LATITUDE><LONGITUDE>-75.650385</LONGITUDE><DIRECTION>-1.0</DIRECTION><SPEED>0.0</SPEED></Position><Position><GPSID>VIA_3470</GPSID><UTC>2019-08-05T21:29:20.170-04:00</UTC><UTCTIME>1565054960170</UTCTIME><LATITUDE>45.41612</LATITUDE><LONGITUDE>-75.649948</LONGITUDE><DIRECTION>-1.0</DIRECTION><SPEED>0.0</SPEED></Position><Position><GPSID>VIA_4004</GPSID><UTC>2019-08-05T21:29:21.167-04:00</UTC><UTCTIME>1565054961167</UTCTIME><LATITUDE>45.343097</LATITUDE><LONGITUDE>-75.702922</LONGITUDE><DIRECTION>43.6</DIRECTION><SPEED>20.8</SPEED></Position><Position><GPSID>VIA_7314</GPSID><UTC>2019-08-05T21:29:21.336-04:00</UTC><UTCTIME>1565054961336</UTCTIME><LATITUDE>44.636978</LATITUDE><LONGITUDE>-63.568332</LONGITUDE><DIRECTION>-1.0</DIRECTION><SPEED>0.0</SPEED></Position><Position><GPSID>VIA_3461</GPSID><UTC>2019-08-05T21:29:21.527-04:00</UTC><UTCTIME>1565054961527</UTCTIME><LATITUDE>44.868727</LATITUDE><LONGITUDE>-75.29925</LONGITUDE><DIRECTION>59.4</DIRECTION><SPEED>82.2</SPEED></Position><Position><GPSID>VIA_3467</GPSID><UTC>2019-08-05T21:29:22.022-04:00</UTC><UTCTIME>1565054962022</UTCTIME><LATITUDE>45.415797</LATITUDE><LONGITUDE>-75.653005</LONGITUDE><DIRECTION>-1.0</DIRECTION><SPEED>0.0</SPEED></Position><Position><GPSID>VIA_7309</GPSID><UTC>2019-08-05T21:29:22.051-04:00</UTC><UTCTIME>1565054962051</UTCTIME><LATITUDE>44.637553</LATITUDE><LONGITUDE>-63.568168</LONGITUDE><DIRECTION>-1.0</DIRECTION><SPEED>0.0</SPEED></Position><Position><GPSID>VIA_3352</GPSID><UTC>2019-08-05T21:29:22.167-04:00</UTC><UTCTIME>1565054962167</UTCTIME><LATITUDE>44.868595</LATITUDE><LONGITUDE>-75.299512</LONGITUDE><DIRECTION>59.8</DIRECTION><SPEED>82.4</SPEED></Position><Position><GPSID>VIA_4025</GPSID><UTC>2019-08-05T21:29:22.264-04:00</UTC><UTCTIME>1565054962264</UTCTIME><LATITUDE>44.63825</LATITUDE><LONGITUDE>-63.569313</LONGITUDE><DIRECTION>-1.0</DIRECTION><SPEED>0.0</SPEED></Position><Position><GPSID>VIA_3452</GPSID><UTC>2019-08-05T21:29:22.444-04:00</UTC><UTCTIME>1565054962444</UTCTIME><LATITUDE>42.981167</LATITUDE><LONGITUDE>-81.245368</LONGITUDE><DIRECTION>-1.0</DIRECTION><SPEED>0.0</SPEED></Position><Position><GPSID>VIA_3463</GPSID><UTC>2019-08-05T21:29:22.524-04:00</UTC><UTCTIME>1565054962524</UTCTIME><LATITUDE>45.478027</LATITUDE><LONGITUDE>-73.548993</LONGITUDE><DIRECTION>-1.0</DIRECTION><SPEED>0.0</SPEED></Position><Position><GPSID>VIA_3367</GPSID><UTC>2019-08-05T21:29:22.986-04:00</UTC><UTCTIME>1565054962986</UTCTIME><LATITUDE>44.223412</LATITUDE><LONGITUDE>-76.862533</LONGITUDE><DIRECTION>289.6</DIRECTION><SPEED>82.0</SPEED></Position><Position><GPSID>VIA_7301</GPSID><UTC>2019-08-05T21:29:23.001-04:00</UTC><UTCTIME>1565054963001</UTCTIME><LATITUDE>45.484708</LATITUDE><LONGITUDE>-73.543282</LONGITUDE><DIRECTION>-1.0</DIRECTION><SPEED>0.0</SPEED></Position><Position><GPSID>VIA_4003</GPSID><UTC>2019-08-05T21:29:23.242-04:00</UTC><UTCTIME>1565054963242</UTCTIME><LATITUDE>43.608728</LATITUDE><LONGITUDE>-79.50834</LONGITUDE><DIRECTION>-1.0</DIRECTION><SPEED>0.0</SPEED></Position><Position><GPSID>VIA_3477</GPSID><UTC>2019-08-05T21:29:23.620-04:00</UTC><UTCTIME>1565054963620</UTCTIME><LATITUDE>43.146902</LATITUDE><LONGITUDE>-80.260005</LONGITUDE><DIRECTION>263.4</DIRECTION><SPEED>16.7</SPEED></Position><Position><GPSID>VIA_3460</GPSID><UTC>2019-08-05T21:29:23.841-04:00</UTC><UTCTIME>1565054963841</UTCTIME><LATITUDE>43.610368</LATITUDE><LONGITUDE>-79.507837</LONGITUDE><DIRECTION>-1.0</DIRECTION><SPEED>0.0</SPEED></Position><Position><GPSID>VIA_3459</GPSID><UTC>2019-08-05T21:29:23.934-04:00</UTC><UTCTIME>1565054963934</UTCTIME><LATITUDE>44.223463</LATITUDE><LONGITUDE>-76.862713</LONGITUDE><DIRECTION>289.5</DIRECTION><SPEED>82.0</SPEED></Position><Position><GPSID>VIA_3465</GPSID><UTC>2019-08-05T21:29:24.005-04:00</UTC><UTCTIME>1565054964005</UTCTIME><LATITUDE>45.479488</LATITUDE><LONGITUDE>-73.5466</LONGITUDE><DIRECTION>-1.0</DIRECTION><SPEED>0.0</SPEED></Position><Position><GPSID>VIA_4009</GPSID><UTC>2019-08-05T21:29:24.047-04:00</UTC><UTCTIME>1565054964047</UTCTIME><LATITUDE>44.311515</LATITUDE><LONGITUDE>-76.3929</LONGITUDE><DIRECTION>56.9</DIRECTION><SPEED>80.4</SPEED></Position><Position><GPSID>VIA_3462</GPSID><UTC>2019-08-05T21:29:24.097-04:00</UTC><UTCTIME>1565054964097</UTCTIME><LATITUDE>43.644218</LATITUDE><LONGITUDE>-79.380115</LONGITUDE><DIRECTION>-1.0</DIRECTION><SPEED>0.0</SPEED></Position><Position><GPSID>VIA_3466</GPSID><UTC>2019-08-05T21:29:24.136-04:00</UTC><UTCTIME>1565054964136</UTCTIME><LATITUDE>45.481773</LATITUDE><LONGITUDE>-73.545025</LONGITUDE><DIRECTION>-1.0</DIRECTION><SPEED>0.0</SPEED></Position><Position><GPSID>VIA_7313</GPSID><UTC>2019-08-05T21:29:24.836-04:00</UTC><UTCTIME>1565054964836</UTCTIME><LATITUDE>45.47996</LATITUDE><LONGITUDE>-73.547155</LONGITUDE><DIRECTION>-1.0</DIRECTION><SPEED>0.0</SPEED></Position><Position><GPSID>VIA_3471</GPSID><UTC>2019-08-05T21:29:25.311-04:00</UTC><UTCTIME>1565054965311</UTCTIME><LATITUDE>46.748542</LATITUDE><LONGITUDE>-71.332283</LONGITUDE><DIRECTION>248.8</DIRECTION><SPEED>19.4</SPEED></Position><Position><GPSID>VIA_3468</GPSID><UTC>2019-08-05T21:29:25.584-04:00</UTC><UTCTIME>1565054965584</UTCTIME><LATITUDE>45.344875</LATITUDE><LONGITUDE>-74.0951</LONGITUDE><DIRECTION>55.1</DIRECTION><SPEED>66.2</SPEED></Position><Position><GPSID>VIA_3455</GPSID><UTC>2019-08-05T21:29:25.993-04:00</UTC><UTCTIME>1565054965993</UTCTIME><LATITUDE>43.244847</LATITUDE><LONGITUDE>-80.05746</LONGITUDE><DIRECTION>85.1</DIRECTION><SPEED>13.5</SPEED></Position><Position><GPSID>VIA_7307</GPSID><UTC>2019-08-05T21:29:26.602-04:00</UTC><UTCTIME>1565054966602</UTCTIME><LATITUDE>45.415748</LATITUDE><LONGITUDE>-75.65048</LONGITUDE><DIRECTION>-1.0</DIRECTION><SPEED>0.0</SPEED></Position><Position><GPSID>VIA_4019</GPSID><UTC>2019-08-05T21:29:26.817-04:00</UTC><UTCTIME>1565054966817</UTCTIME><LATITUDE>0.0</LATITUDE><LONGITUDE>0.0</LONGITUDE><DIRECTION>-1.0</DIRECTION><SPEED>0.0</SPEED></Position><Position><GPSID>VIA_4026</GPSID><UTC>2019-08-05T21:29:26.924-04:00</UTC><UTCTIME>1565054966924</UTCTIME><LATITUDE>43.939063</LATITUDE><LONGITUDE>-79.434095</LONGITUDE><DIRECTION>-1.0</DIRECTION><SPEED>0.0</SPEED></Position><Position><GPSID>VIA_3469</GPSID><UTC>2019-08-05T21:29:26.954-04:00</UTC><UTCTIME>1565054966954</UTCTIME><LATITUDE>44.252162</LATITUDE><LONGITUDE>-76.962775</LONGITUDE><DIRECTION>75.2</DIRECTION><SPEED>62.8</SPEED></Position><Position><GPSID>VIA_3475</GPSID><UTC>2019-08-05T21:29:27.461-04:00</UTC><UTCTIME>1565054967461</UTCTIME><LATITUDE>46.819877</LATITUDE><LONGITUDE>-71.214772</LONGITUDE><DIRECTION>-1.0</DIRECTION><SPEED>0.0</SPEED></Position><Position><GPSID>VIA_4002</GPSID><UTC>2019-08-05T21:29:27.542-04:00</UTC><UTCTIME>1565054967542</UTCTIME><LATITUDE>44.216388</LATITUDE><LONGITUDE>-77.168247</LONGITUDE><DIRECTION>256.1</DIRECTION><SPEED>78.6</SPEED></Position><Position><GPSID>VIA_3464</GPSID><UTC>2019-08-05T21:29:27.712-04:00</UTC><UTCTIME>1565054967712</UTCTIME><LATITUDE>44.914943</LATITUDE><LONGITUDE>-76.024705</LONGITUDE><DIRECTION>351.6</DIRECTION><SPEED>32.6</SPEED></Position><Position><GPSID>VIA_7308</GPSID><UTC>2019-08-05T21:29:27.974-04:00</UTC><UTCTIME>1565054967974</UTCTIME><LATITUDE>45.476012</LATITUDE><LONGITUDE>-73.551115</LONGITUDE><DIRECTION>-1.0</DIRECTION><SPEED>0.0</SPEED></Position><Position><GPSID>VIA_3451</GPSID><UTC>2019-08-05T21:29:28.013-04:00</UTC><UTCTIME>1565054968013</UTCTIME><LATITUDE>43.244907</LATITUDE><LONGITUDE>-80.056975</LONGITUDE><DIRECTION>84.0</DIRECTION><SPEED>13.5</SPEED></Position><Position><GPSID>VIA_4005</GPSID><UTC>2019-08-05T21:29:28.131-04:00</UTC><UTCTIME>1565054968131</UTCTIME><LATITUDE>45.481073</LATITUDE><LONGITUDE>-73.545457</LONGITUDE><DIRECTION>-1.0</DIRECTION><SPEED>0.0</SPEED></Position><Position><GPSID>VIA_4028</GPSID><UTC>2019-08-05T21:29:28.436-04:00</UTC><UTCTIME>1565054968436</UTCTIME><LATITUDE>44.634522</LATITUDE><LONGITUDE>-63.569158</LONGITUDE><DIRECTION>-1.0</DIRECTION><SPEED>0.0</SPEED></Position><Position><GPSID>VIA_3456</GPSID><UTC>2019-08-05T21:29:28.625-04:00</UTC><UTCTIME>1565054968625</UTCTIME><LATITUDE>42.323323</LATITUDE><LONGITUDE>-82.401633</LONGITUDE><DIRECTION>248.8</DIRECTION><SPEED>28.9</SPEED></Position><Position><GPSID>VIA_3476</GPSID><UTC>2019-08-05T21:29:28.940-04:00</UTC><UTCTIME>1565054968940</UTCTIME><LATITUDE>42.988063</LATITUDE><LONGITUDE>-81.330217</LONGITUDE><DIRECTION>283.8</DIRECTION><SPEED>20.1</SPEED></Position><Position><GPSID>VIA_3458</GPSID><UTC>2019-08-05T21:29:29.006-04:00</UTC><UTCTIME>1565054969006</UTCTIME><LATITUDE>42.981075</LATITUDE><LONGITUDE>-81.245642</LONGITUDE><DIRECTION>-1.0</DIRECTION><SPEED>0.0</SPEED></Position><Position><GPSID>VIA_4007</GPSID><UTC>2019-08-05T21:29:29.058-04:00</UTC><UTCTIME>1565054969058</UTCTIME><LATITUDE>43.367555</LATITUDE><LONGITUDE>-80.756632</LONGITUDE><DIRECTION>66.9</DIRECTION><SPEED>9.8</SPEED></Position><Position><GPSID>VIA_4008</GPSID><UTC>2019-08-05T21:29:29.493-04:00</UTC><UTCTIME>1565054969493</UTCTIME><LATITUDE>43.765368</LATITUDE><LONGITUDE>-79.148995</LONGITUDE><DIRECTION>243.1</DIRECTION><SPEED>63.7</SPEED></Position><Position><GPSID>VIA_3472</GPSID><UTC>2019-08-05T21:29:29.671-04:00</UTC><UTCTIME>1565054969671</UTCTIME><LATITUDE>45.415997</LATITUDE><LONGITUDE>-75.650385</LONGITUDE><DIRECTION>-1.0</DIRECTION><SPEED>0.0</SPEED></Position><Position><GPSID>VIA_3470</GPSID><UTC>2019-08-05T21:29:30.170-04:00</UTC><UTCTIME>1565054970170</UTCTIME><LATITUDE>45.416122</LATITUDE><LONGITUDE>-75.649948</LONGITUDE><DIRECTION>-1.0</DIRECTION><SPEED>0.0</SPEED></Position></PositionList>
