{"2 (08-02)":{"departed":true,"times":[{"station":"ASHCROFT","estimated":"&mdash;","scheduled":"2019-08-03T05:32:00Z","eta":"&mdash;"},{"station":"ARMSTRONG","estimated":"2019-08-06T01:26:08Z","scheduled":"2019-08-05T14:57:00Z","eta":"2 mins","diff":"bad","diffMin":629},{"station":"MUD RIVER","estimated":"&mdash;","scheduled":"2019-08-05T15:29:00Z","eta":"&mdash;","diff":"goo","diffMin":629},{"station":"FERLAND","estimated":"&mdash;","scheduled":"2019-08-05T15:37:00Z","eta":"&mdash;","diff":"goo","diffMin":629},{"station":"AUDEN","estimated":"&mdash;","scheduled":"2019-08-05T16:14:00Z","eta":"&mdash;","diff":"goo","diffMin":629},{"station":"NAKINA","estimated":"&mdash;","scheduled":"2019-08-05T17:20:00Z","eta":"&mdash;","diff":"goo","diffMin":629},{"station":"LONGLAC","estimated":"&mdash;","scheduled":"2019-08-05T18:11:00Z","eta":"&mdash;","diff":"goo","diffMin":629},{"station":"CARAMAT","estimated":"&mdash;","scheduled":"2019-08-05T18:39:00Z","eta":"&mdash;","diff":"goo","diffMin":629},{"station":"HILLSPORT","estimated":"&mdash;","scheduled":"2019-08-05T19:29:00Z","eta":"&mdash;","diff":"goo","diffMin":629},{"station":"HORNEPAYNE","estimated":"&mdash;","scheduled":"2019-08-05T21:44:00Z","eta":"&mdash;","diff":"goo","diffMin":629},{"station":"OBA","estimated":"&mdash;","scheduled":"2019-08-05T23:30:00Z","eta":"&mdash;","diff":"goo","diffMin":629},{"station":"ELSAS","estimated":"&mdash;","scheduled":"2019-08-06T01:04:00Z","eta":"&mdash;","diff":"goo","diffMin":629},{"station":"FOLEYET","estimated":"&mdash;","scheduled":"2019-08-06T02:27:00Z","eta":"&mdash;","diff":"goo","diffMin":629},{"station":"GOGAMA","estimated":"&mdash;","scheduled":"2019-08-06T04:02:00Z","eta":"&mdash;","diff":"goo","diffMin":629},{"station":"WESTREE","estimated":"&mdash;","scheduled":"2019-08-06T04:35:00Z","eta":"&mdash;","diff":"goo","diffMin":629},{"station":"RUEL","estimated":"&mdash;","scheduled":"2019-08-06T04:52:00Z","eta":"&mdash;","diff":"goo","diffMin":629},{"station":"FELIX","estimated":"&mdash;","scheduled":"2019-08-06T05:00:00Z","eta":"&mdash;","diff":"goo","diffMin":629},{"station":"MCKEE'S CAMP","estimated":"&mdash;","scheduled":"2019-08-06T05:20:00Z","eta":"&mdash;","diff":"goo","diffMin":629},{"station":"LAFOREST","estimated":"&mdash;","scheduled":"2019-08-06T05:33:00Z","eta":"&mdash;","diff":"goo","diffMin":629},{"station":"CAPREOL","estimated":"&mdash;","scheduled":"2019-08-06T07:47:00Z","eta":"&mdash;","diff":"goo","diffMin":629},{"station":"SUDBURY (JCT.)","estimated":"&mdash;","scheduled":"2019-08-06T08:49:00Z","eta":"&mdash;","diff":"goo","diffMin":629},{"station":"PARRY SOUND","estimated":"&mdash;","scheduled":"2019-08-06T12:42:00Z","eta":"&mdash;","diff":"goo","diffMin":629},{"station":"WASHAGO","estimated":"&mdash;","scheduled":"2019-08-06T14:59:00Z","eta":"&mdash;","diff":"goo","diffMin":629}]},"1 (08-04)":{"lat":49.9723,"lng":-94.5225,"speed":11,"direction":null,"poll":"2019-08-06T01:21:31Z","departed":true,"pollMin":2,"times":[{"station":"MINAKI","estimated":"2019-08-06T01:32:29Z","scheduled":"2019-08-05T20:44:00Z","eta":"8 mins","diff":"bad","diffMin":288},{"station":"OTTERMERE","estimated":"2019-08-06T01:49:29Z","scheduled":"2019-08-05T21:01:00Z","eta":"25 mins","diff":"bad","diffMin":288},{"station":"MALACHI","estimated":"&mdash;","scheduled":"2019-08-05T21:07:00Z","eta":"&mdash;","diff":"goo","diffMin":288},{"station":"COPELANDS LANDING","estimated":"&mdash;","scheduled":"2019-08-05T21:09:00Z","eta":"&mdash;","diff":"goo","diffMin":288},{"station":"RICE LAKE","estimated":"&mdash;","scheduled":"2019-08-05T21:12:00Z","eta":"&mdash;","diff":"goo","diffMin":288},{"station":"WINNITOBA","estimated":"&mdash;","scheduled":"2019-08-05T21:26:00Z","eta":"&mdash;","diff":"goo","diffMin":288},{"station":"OPHIR","estimated":"&mdash;","scheduled":"2019-08-05T21:31:00Z","eta":"&mdash;","diff":"goo","diffMin":288},{"station":"BRERETON LAKE","estimated":"&mdash;","scheduled":"2019-08-05T21:49:00Z","eta":"&mdash;","diff":"goo","diffMin":288},{"station":"ELMA","estimated":"&mdash;","scheduled":"2019-08-05T22:10:00Z","eta":"&mdash;","diff":"goo","diffMin":288},{"station":"WINNIPEG","estimated":"&mdash;","scheduled":"2019-08-06T00:30:00Z","eta":"&mdash;","diff":"goo","diffMin":288},{"station":"PORTAGE LA PRAIRIE","estimated":"&mdash;","scheduled":"2019-08-06T04:04:00Z","eta":"&mdash;","diff":"goo","diffMin":288},{"station":"RIVERS","estimated":"&mdash;","scheduled":"2019-08-06T06:31:00Z","eta":"&mdash;","diff":"goo","diffMin":288},{"station":"MELVILLE","estimated":"&mdash;","scheduled":"2019-08-06T10:54:00Z","eta":"&mdash;","diff":"goo","diffMin":288},{"station":"WATROUS","estimated":"&mdash;","scheduled":"2019-08-06T13:54:00Z","eta":"&mdash;","diff":"goo","diffMin":288}]},"2 (08-05)":{"lat":49.4072,"lng":-121.4312,"speed":47,"direction":null,"poll":"2019-08-06T01:21:40Z","departed":true,"pollMin":1,"times":[{"station":"NORTH BEND","estimated":"2019-08-06T03:27:17Z","scheduled":"2019-08-06T02:46:00Z","eta":"2h03","diff":"bad","diffMin":41},{"station":"ASHCROFT","estimated":"2019-08-06T06:13:17Z","scheduled":"2019-08-06T05:32:00Z","eta":"4h49","diff":"bad","diffMin":41},{"station":"KAMLOOPS NORTH","estimated":"&mdash;","scheduled":"2019-08-06T07:17:00Z","eta":"&mdash;","diff":"goo","diffMin":41},{"station":"CLEARWATER","estimated":"&mdash;","scheduled":"2019-08-06T09:58:00Z","eta":"&mdash;","diff":"goo","diffMin":41},{"station":"BLUE RIVER","estimated":"&mdash;","scheduled":"2019-08-06T12:11:00Z","eta":"&mdash;","diff":"goo","diffMin":41},{"station":"VALEMOUNT","estimated":"&mdash;","scheduled":"2019-08-06T14:01:00Z","eta":"&mdash;","diff":"goo","diffMin":41}]},"692":{"lat":50.9657,"lng":-99.6365,"speed":96,"direction":null,"poll":"2019-08-06T01:21:38Z","departed":true,"pollMin":1,"times":[{"station":"LAURIER","estimated":"2019-08-06T01:29:11Z","scheduled":"2019-08-05T17:38:00Z","eta":"5 mins","diff":"bad","diffMin":471},{"station":"MCCREARY","estimated":"2019-08-06T01:45:11Z","scheduled":"2019-08-05T17:54:00Z","eta":"21 mins","diff":"bad","diffMin":471},{"station":"GLENELLA","estimated":"2019-08-06T02:25:11Z","scheduled":"2019-08-05T18:34:00Z","eta":"1h01","diff":"bad","diffMin":471},{"station":"PLUMAS","estimated":"2019-08-06T02:57:11Z","scheduled":"2019-08-05T19:06:00Z","eta":"1h33","diff":"bad","diffMin":471},{"station":"GLADSTONE","estimated":"2019-08-06T03:42:11Z","scheduled":"2019-08-05T19:51:00Z","eta":"2h18","diff":"bad","diffMin":471},{"station":"PORTAGE LA PRAIRIE","estimated":"2019-08-06T04:28:11Z","scheduled":"2019-08-05T20:37:00Z","eta":"3h04","diff":"bad","diffMin":471},{"station":"WINNIPEG","estimated":"2019-08-06T05:36:11Z","scheduled":"2019-08-05T21:45:00Z","eta":"4h12","diff":"bad","diffMin":471}]},"693":{"departed":true,"times":[{"station":"PIT SIDING","estimated":"2019-08-06T01:35:00Z","scheduled":"2019-08-06T01:35:00Z","eta":"11 mins","diff":"goo","diffMin":0},{"station":"ILFORD","estimated":"2019-08-06T02:36:00Z","scheduled":"2019-08-06T02:36:00Z","eta":"1h12","diff":"goo","diffMin":0},{"station":"WIVENHOE","estimated":"2019-08-06T03:13:00Z","scheduled":"2019-08-06T03:13:00Z","eta":"1h49","diff":"goo","diffMin":0},{"station":"GILLAM","estimated":"2019-08-06T04:00:01Z","scheduled":"2019-08-06T04:00:01Z","eta":"2h36","diff":"goo","diffMin":0},{"station":"BIRD","estimated":"2019-08-06T05:29:00Z","scheduled":"2019-08-06T05:29:00Z","eta":"4h05","diff":"goo","diffMin":0},{"station":"AMERY","estimated":"2019-08-06T05:52:00Z","scheduled":"2019-08-06T05:52:00Z","eta":"4h28","diff":"goo","diffMin":0},{"station":"WEIR RIVER","estimated":"2019-08-06T06:43:00Z","scheduled":"2019-08-06T06:43:00Z","eta":"5h19","diff":"goo","diffMin":0},{"station":"THIBAUDEAU","estimated":"2019-08-06T08:00:00Z","scheduled":"2019-08-06T08:00:00Z","eta":"6h36","diff":"goo","diffMin":0},{"station":"HERCHMER","estimated":"2019-08-06T09:26:00Z","scheduled":"2019-08-06T09:26:00Z","eta":"8h02","diff":"goo","diffMin":0},{"station":"O'DAY","estimated":"2019-08-06T10:05:00Z","scheduled":"2019-08-06T10:05:00Z","eta":"8h41","diff":"goo","diffMin":0},{"station":"M'CLINTOCK","estimated":"2019-08-06T10:50:00Z","scheduled":"2019-08-06T10:50:00Z","eta":"9h26","diff":"goo","diffMin":0},{"station":"CHESNAYE","estimated":"2019-08-06T12:06:00Z","scheduled":"2019-08-06T12:06:00Z","eta":"10h42","diff":"goo","diffMin":0},{"station":"TIDAL","estimated":"2019-08-06T13:37:00Z","scheduled":"2019-08-06T13:37:00Z","eta":"12h13","diff":"goo","diffMin":0},{"station":"CHURCHILL","estimated":"2019-08-06T14:00:00Z","scheduled":"2019-08-06T14:00:00Z","eta":"12h36","diff":"goo","diffMin":0}]},"5":{"lat":54.8588,"lng":-127.2705,"speed":40,"direction":null,"poll":"2019-08-06T01:08:05Z","departed":true,"pollMin":15,"pollRadius":10200,"times":[{"station":"NEW HAZELTON","estimated":"2019-08-06T02:12:43Z","scheduled":"2019-08-05T22:37:00Z","eta":"49 mins","diff":"bad","diffMin":215},{"station":"KITWANGA","estimated":"2019-08-06T03:02:43Z","scheduled":"2019-08-05T23:27:00Z","eta":"1h39","diff":"bad","diffMin":215},{"station":"CEDARVALE","estimated":"2019-08-06T03:26:43Z","scheduled":"2019-08-05T23:51:00Z","eta":"2h03","diff":"bad","diffMin":215},{"station":"DORREEN","estimated":"2019-08-06T03:47:43Z","scheduled":"2019-08-06T00:12:00Z","eta":"2h24","diff":"bad","diffMin":215},{"station":"PACIFIC","estimated":"2019-08-06T03:56:43Z","scheduled":"2019-08-06T00:21:00Z","eta":"2h33","diff":"bad","diffMin":215},{"station":"USK","estimated":"2019-08-06T04:15:43Z","scheduled":"2019-08-06T00:40:00Z","eta":"2h52","diff":"bad","diffMin":215},{"station":"TERRACE","estimated":"2019-08-06T04:35:43Z","scheduled":"2019-08-06T01:00:00Z","eta":"3h12","diff":"bad","diffMin":215},{"station":"KWINITSA","estimated":"2019-08-06T05:44:43Z","scheduled":"2019-08-06T02:09:00Z","eta":"4h21","diff":"bad","diffMin":215},{"station":"PRINCE RUPERT","estimated":"2019-08-06T07:00:43Z","scheduled":"2019-08-06T03:25:00Z","eta":"5h37","diff":"bad","diffMin":215}]},"88":{"lat":43.3659,"lng":-80.8491,"speed":111,"direction":90,"poll":"2019-08-06T01:23:28Z","departed":true,"pollMin":0,"times":[{"station":"KITCHENER","estimated":"2019-08-06T01:49:35Z","scheduled":"2019-08-06T01:40:00Z","eta":"26 mins","diff":"med","diffMin":9},{"station":"GUELPH","estimated":"2019-08-06T02:19:35Z","scheduled":"2019-08-06T02:10:00Z","eta":"56 mins","diff":"med","diffMin":9},{"station":"GEORGETOWN","estimated":"2019-08-06T02:45:35Z","scheduled":"2019-08-06T02:36:00Z","eta":"1h22","diff":"med","diffMin":9},{"station":"BRAMPTON","estimated":"2019-08-06T02:55:35Z","scheduled":"2019-08-06T02:46:00Z","eta":"1h32","diff":"med","diffMin":9},{"station":"TORONTO","estimated":"2019-08-06T03:26:35Z","scheduled":"2019-08-06T03:17:00Z","eta":"2h03","diff":"med","diffMin":9}]},"79":{"lat":43.1559,"lng":-80.2498,"speed":37,"direction":226,"poll":"2019-08-06T01:23:22Z","departed":true,"pollMin":0,"times":[{"station":"BRANTFORD","estimated":"2019-08-06T01:25:23Z","scheduled":"2019-08-06T00:50:00Z","eta":"1 min","diff":"bad","diffMin":35},{"station":"WOODSTOCK","estimated":"2019-08-06T01:52:23Z","scheduled":"2019-08-06T01:17:00Z","eta":"28 mins","diff":"bad","diffMin":35},{"station":"INGERSOLL","estimated":"2019-08-06T02:05:23Z","scheduled":"2019-08-06T01:30:00Z","eta":"41 mins","diff":"bad","diffMin":35},{"station":"LONDON","estimated":"2019-08-06T02:27:23Z","scheduled":"2019-08-06T01:52:00Z","eta":"1h03","diff":"bad","diffMin":35},{"station":"GLENCOE","estimated":"2019-08-06T03:00:23Z","scheduled":"2019-08-06T02:25:00Z","eta":"1h36","diff":"bad","diffMin":35},{"station":"CHATHAM","estimated":"2019-08-06T03:32:23Z","scheduled":"2019-08-06T02:57:00Z","eta":"2h08","diff":"bad","diffMin":35},{"station":"WINDSOR","estimated":"2019-08-06T04:19:23Z","scheduled":"2019-08-06T03:44:00Z","eta":"2h55","diff":"bad","diffMin":35}]},"650":{"lat":44.2222,"lng":-77.1356,"speed":138,"direction":76,"poll":"2019-08-06T01:23:26Z","departed":true,"pollMin":0,"times":[{"station":"KINGSTON","estimated":"2019-08-06T01:47:47Z","scheduled":"2019-08-06T01:56:00Z","eta":"24 mins","diff":"goo","diffMin":0}]},"54":{"lat":44.9064,"lng":-76.0184,"speed":0,"direction":null,"poll":"2019-08-06T01:23:27Z","departed":true,"pollMin":0,"times":[{"station":"FALLOWFIELD","estimated":"2019-08-06T01:49:34Z","scheduled":"2019-08-06T01:46:00Z","eta":"26 mins","diff":"goo","diffMin":3},{"station":"OTTAWA","estimated":"2019-08-06T02:10:34Z","scheduled":"2019-08-06T02:07:00Z","eta":"47 mins","diff":"goo","diffMin":3}]},"68":{"lat":45.2724,"lng":-74.238,"speed":135,"direction":54,"poll":"2019-08-06T01:23:25Z","departed":true,"pollMin":0,"times":[{"station":"DORVAL","estimated":"2019-08-06T01:47:16Z","scheduled":"2019-08-06T01:27:00Z","eta":"23 mins","diff":"bad","diffMin":20},{"station":"MONTR\u00c9AL","estimated":"2019-08-06T02:09:16Z","scheduled":"2019-08-06T01:49:00Z","eta":"45 mins","diff":"bad","diffMin":20}]},"28":{"lat":46.7541,"lng":-71.2982,"speed":0,"direction":null,"poll":"2019-08-06T01:23:25Z","departed":true,"pollMin":0,"times":[{"station":"QU\u00c9BEC","estimated":"2019-08-06T01:54:00Z","scheduled":"2019-08-06T01:54:00Z","eta":"30 mins","diff":"goo","diffMin":0}]},"647":{"lat":43.824,"lng":-79.1005,"speed":42,"direction":237,"poll":"2019-08-06T01:23:29Z","departed":true,"pollMin":0,"times":[{"station":"TORONTO","estimated":"2019-08-06T01:42:49Z","scheduled":"2019-08-06T01:45:00Z","eta":"19 mins","diff":"goo","diffMin":0}]},"87":{"lat":42.9769,"lng":-81.2642,"speed":57,"direction":266,"poll":"2019-08-06T01:23:28Z","departed":true,"pollMin":0,"times":[{"station":"STRATHROY","estimated":"2019-08-06T01:41:54Z","scheduled":"2019-08-06T01:35:00Z","eta":"18 mins","diff":"med","diffMin":6},{"station":"WYOMING","estimated":"2019-08-06T02:09:54Z","scheduled":"2019-08-06T02:03:00Z","eta":"46 mins","diff":"med","diffMin":6},{"station":"SARNIA","estimated":"2019-08-06T02:26:54Z","scheduled":"2019-08-06T02:20:00Z","eta":"1h03","diff":"med","diffMin":6}]},"48":{"lat":44.2626,"lng":-76.5033,"speed":98,"direction":115,"poll":"2019-08-06T01:23:24Z","departed":true,"pollMin":0,"times":[{"station":"GANANOQUE","estimated":"2019-08-06T01:41:49Z","scheduled":"2019-08-06T01:37:00Z","eta":"18 mins","diff":"goo","diffMin":4},{"station":"BROCKVILLE","estimated":"2019-08-06T02:05:49Z","scheduled":"2019-08-06T02:01:00Z","eta":"42 mins","diff":"goo","diffMin":4},{"station":"SMITHS FALLS","estimated":"2019-08-06T02:35:49Z","scheduled":"2019-08-06T02:31:00Z","eta":"1h12","diff":"goo","diffMin":4},{"station":"FALLOWFIELD","estimated":"2019-08-06T03:02:49Z","scheduled":"2019-08-06T02:58:00Z","eta":"1h39","diff":"goo","diffMin":4},{"station":"OTTAWA","estimated":"2019-08-06T03:20:49Z","scheduled":"2019-08-06T03:16:00Z","eta":"1h57","diff":"goo","diffMin":4}]},"668":{"lat":44.7776,"lng":-75.4356,"speed":148,"direction":54,"poll":"2019-08-06T01:23:21Z","departed":true,"pollMin":0,"times":[{"station":"CORNWALL","estimated":"2019-08-06T01:53:25Z","scheduled":"2019-08-06T01:49:00Z","eta":"29 mins","diff":"goo","diffMin":4},{"station":"DORVAL","estimated":"2019-08-06T02:41:25Z","scheduled":"2019-08-06T02:37:00Z","eta":"1h17","diff":"goo","diffMin":4},{"station":"MONTR\u00c9AL","estimated":"2019-08-06T03:03:25Z","scheduled":"2019-08-06T02:59:00Z","eta":"1h39","diff":"goo","diffMin":4}]},"75":{"lat":42.3518,"lng":-82.3022,"speed":138,"direction":248,"poll":"2019-08-06T01:23:28Z","departed":true,"pollMin":0,"times":[{"station":"WINDSOR","estimated":"2019-08-06T02:00:30Z","scheduled":"2019-08-06T01:56:00Z","eta":"36 mins","diff":"goo","diffMin":4}]},"78":{"lat":43.2417,"lng":-80.1005,"speed":35,"direction":84,"poll":"2019-08-06T01:23:28Z","departed":true,"pollMin":0,"times":[{"station":"ALDERSHOT","estimated":"2019-08-06T01:38:39Z","scheduled":"2019-08-06T01:13:00Z","eta":"15 mins","diff":"bad","diffMin":25},{"station":"OAKVILLE","estimated":"2019-08-06T01:52:39Z","scheduled":"2019-08-06T01:27:00Z","eta":"29 mins","diff":"bad","diffMin":25},{"station":"TORONTO","estimated":"2019-08-06T02:16:39Z","scheduled":"2019-08-06T01:51:00Z","eta":"53 mins","diff":"bad","diffMin":25}]},"69":{"lat":43.6451,"lng":-79.3801,"speed":0,"direction":null,"poll":"2019-08-06T01:23:24Z","departed":true,"pollMin":0,"times":[{"station":"OAKVILLE","estimated":"2019-08-06T02:01:35Z","scheduled":"2019-08-06T01:55:00Z","eta":"38 mins","diff":"med","diffMin":6},{"station":"ALDERSHOT","estimated":"2019-08-06T02:15:35Z","scheduled":"2019-08-06T02:09:00Z","eta":"52 mins","diff":"med","diffMin":6}]},"669":{"lat":44.2267,"lng":-76.7192,"speed":144,"direction":256,"poll":"2019-08-06T01:23:22Z","departed":true,"pollMin":0,"times":[{"station":"OSHAWA","estimated":"2019-08-06T03:00:00Z","scheduled":"2019-08-06T03:02:00Z","eta":"1h36","diff":"goo","diffMin":0},{"station":"TORONTO","estimated":"2019-08-06T03:33:00Z","scheduled":"2019-08-06T03:33:00Z","eta":"2h09","diff":"goo","diffMin":0}]},"59":{"lat":44.2453,"lng":-76.9963,"speed":137,"direction":249,"poll":"2019-08-06T01:23:27Z","departed":true,"pollMin":0,"times":[{"station":"BELLEVILLE","estimated":"2019-08-06T01:38:40Z","scheduled":"2019-08-06T01:20:00Z","eta":"15 mins","diff":"bad","diffMin":18},{"station":"TRENTON JCT.","estimated":"2019-08-06T01:50:40Z","scheduled":"2019-08-06T01:32:00Z","eta":"27 mins","diff":"bad","diffMin":18},{"station":"COBOURG","estimated":"2019-08-06T02:17:40Z","scheduled":"2019-08-06T01:59:00Z","eta":"54 mins","diff":"bad","diffMin":18},{"station":"OSHAWA","estimated":"2019-08-06T02:49:40Z","scheduled":"2019-08-06T02:31:00Z","eta":"1h26","diff":"bad","diffMin":18},{"station":"GUILDWOOD","estimated":"2019-08-06T03:06:40Z","scheduled":"2019-08-06T02:48:00Z","eta":"1h43","diff":"bad","diffMin":18},{"station":"TORONTO","estimated":"2019-08-06T03:25:40Z","scheduled":"2019-08-06T03:07:00Z","eta":"2h02","diff":"bad","diffMin":18}]}}